edl/__init__.py
edl/cli/__init__.py
edl/cli/feed.py
edl/cli/feeds.py
edl/cli/repo.py
edl/cli/stage.py
edl/config/logging.conf
edl/external/__init__.py
edl/external/xmltodict.py
edl/resources/__init__.py
edl/resources/db.py
edl/resources/exec.py
edl/resources/filesystem.py
edl/resources/log.py
edl/resources/save.py
edl/resources/state.py
edl/resources/time.py
edl/resources/web.py
edl/resources/xmlparser.py
edl/resources/zp.py
edl/templates/LICENSE
edl/templates/Makefile
edl/templates/README.md
edl/templates/gitignore
edl/templates/manifest.json
edl/templates/db/state.txt
edl/templates/save/state.txt
edl/templates/src/10_down.py
edl/templates/src/20_unzp.py
edl/templates/src/30_pars.py
edl/templates/src/40_inse.py
edl/templates/src/50_save.py
edl/templates/src/60_dist.sh
edl/templates/src/70_arch.py
edl/templates/xml/state.txt
edl/templates/zip/state.txt
energy_dashboard_library-0.48.dist-info/LICENSE
energy_dashboard_library-0.48.dist-info/METADATA
energy_dashboard_library-0.48.dist-info/WHEEL
energy_dashboard_library-0.48.dist-info/entry_points.txt
energy_dashboard_library-0.48.dist-info/top_level.txt
energy_dashboard_library-0.48.dist-info/RECORD
