Metadata-Version: 2.1
Name: energy-dashboard-library
Version: 0.48
Summary: Energy Dashboard Library
Home-page: http://github.com/energy-analytics-project/energy-dashboard-lib
Author: Todd Greenwood-Geer (Enviro Software Solutions, LLC)
Author-email: pub+github@zwrob.com
License: UNKNOWN
Platform: UNKNOWN
Classifier: Development Status :: 3 - Alpha
Classifier: Intended Audience :: Developers
Classifier: Topic :: Software Development :: Build Tools
Classifier: License :: OSI Approved :: GNU General Public License v3 or later (GPLv3+)
Classifier: Programming Language :: Python :: 3.6
Requires-Dist: idna (==2.8)
Requires-Dist: requests (==2.22.0)
Requires-Dist: urllib3 (==1.25.3)
Requires-Dist: requests
Requires-Dist: Jinja2
